putstr/__init__.py
putstr/puts.py
putstr-1.0.1.dist-info/METADATA
putstr-1.0.1.dist-info/WHEEL
putstr-1.0.1.dist-info/top_level.txt
putstr-1.0.1.dist-info/RECORD
