Metadata-Version: 2.1
Name: putstr
Version: 1.0.1
Requires-Dist: setuptools >=61.1.1
